tsp_client/__init__.py
tsp_client/algorithms.py
tsp_client/exceptions.py
tsp_client/py.typed
tsp_client/signer.py
tsp_client/verifier.py
tsp_client/version.py
tsp_client-0.2.1.dist-info/LICENSE
tsp_client-0.2.1.dist-info/METADATA
tsp_client-0.2.1.dist-info/NOTICE
tsp_client-0.2.1.dist-info/WHEEL
tsp_client-0.2.1.dist-info/top_level.txt
tsp_client-0.2.1.dist-info/RECORD
