Metadata-Version: 2.1
Name: tsp-client
Version: 0.2.1
Summary: An IETF Time-Stamp Protocol (TSP) (RFC 3161) client
Home-page: https://github.com/pyauth/tsp-client
Author: Andrey Kislyuk
Author-email: kislyuk@gmail.com
License: Apache Software License
Project-URL: Documentation, https://pyauth.github.io/tsp-client/
Project-URL: Change log, https://github.com/pyauth/tsp-client/blob/main/Changes.rst
Project-URL: Issue tracker, https://github.com/pyauth/tsp-client/issues
Platform: MacOS X
Platform: Posix
Classifier: Intended Audience :: Developers
Classifier: License :: OSI Approved :: Apache Software License
Classifier: Operating System :: MacOS :: MacOS X
Classifier: Operating System :: POSIX
Classifier: Programming Language :: Python
Classifier: Programming Language :: Python :: 3.8
Classifier: Programming Language :: Python :: 3.9
Classifier: Programming Language :: Python :: 3.10
Classifier: Programming Language :: Python :: 3.11
Classifier: Programming Language :: Python :: 3.12
Classifier: Programming Language :: Python :: 3.13
Classifier: Topic :: Software Development :: Libraries :: Python Modules
License-File: LICENSE
License-File: NOTICE
Requires-Dist: asn1crypto>=1.4.0
Requires-Dist: requests>=2.25.1
Requires-Dist: pyOpenSSL<24,>=21.0.0
Provides-Extra: tests
Requires-Dist: ruff; extra == "tests"
Requires-Dist: coverage; extra == "tests"
Requires-Dist: build; extra == "tests"
Requires-Dist: wheel; extra == "tests"
Requires-Dist: mypy; extra == "tests"
